devoud/__init__.py
devoud/__main__.py
devoud/app.py
devoud/browser/__init__.py
devoud/browser/bookmarks.py
devoud/browser/downloads.py
devoud/browser/filesystem.py
devoud/browser/history.py
devoud/browser/page/__init__.py
devoud/browser/page/abstract_page.py
devoud/browser/page/embedded/__init__.py
devoud/browser/page/embedded/pages/__init__.py
devoud/browser/page/embedded/pages/control.py
devoud/browser/page/embedded/pages/notfound.py
devoud/browser/page/embedded/pages/void.py
devoud/browser/page/embedded/view.py
devoud/browser/page/web/__init__.py
devoud/browser/page/web/adblocker/__init__.py
devoud/browser/page/web/adblocker/rules/easylist.txt
devoud/browser/page/web/adblocker/rules/easyprivacy.txt
devoud/browser/page/web/view.py
devoud/browser/session.py
devoud/browser/settings.py
devoud/browser/styles/__init__.py
devoud/browser/styles/default_themes/ambiance/icons/arrow_down.svg
devoud/browser/styles/default_themes/ambiance/icons/arrow_left.svg
devoud/browser/styles/default_themes/ambiance/icons/arrow_right.svg
devoud/browser/styles/default_themes/ambiance/icons/bookmark.svg
devoud/browser/styles/default_themes/ambiance/icons/bookmark_empty.svg
devoud/browser/styles/default_themes/ambiance/icons/chip.svg
devoud/browser/styles/default_themes/ambiance/icons/clear_list.svg
devoud/browser/styles/default_themes/ambiance/icons/clear_text.svg
devoud/browser/styles/default_themes/ambiance/icons/close.svg
devoud/browser/styles/default_themes/ambiance/icons/close_window.svg
devoud/browser/styles/default_themes/ambiance/icons/dots.svg
devoud/browser/styles/default_themes/ambiance/icons/downloads.svg
devoud/browser/styles/default_themes/ambiance/icons/file.svg
devoud/browser/styles/default_themes/ambiance/icons/folder.svg
devoud/browser/styles/default_themes/ambiance/icons/history.svg
devoud/browser/styles/default_themes/ambiance/icons/home.svg
devoud/browser/styles/default_themes/ambiance/icons/lock.svg
devoud-1.2.0.dist-info/LICENSE
devoud-1.2.0.dist-info/METADATA
devoud-1.2.0.dist-info/WHEEL
devoud-1.2.0.dist-info/entry_points.txt
devoud-1.2.0.dist-info/RECORD
