Metadata-Version: 2.1
Name: devoud
Version: 1.2.0
Summary: A simple Qt Python web browser
Home-page: https://codeberg.org/OneEyedDancer/Devoud
License: GPL-3.0-or-later
Keywords: browser,pyside6,web,qt
Author: OneEyedDancer
Author-email: ooeyd@ya.ru
Requires-Python: >=3.8,<3.12
Classifier: License :: OSI Approved :: GNU General Public License v3 or later (GPLv3+)
Classifier: Programming Language :: Python :: 3
Classifier: Programming Language :: Python :: 3.8
Classifier: Programming Language :: Python :: 3.9
Classifier: Programming Language :: Python :: 3.10
Classifier: Programming Language :: Python :: 3.11
Requires-Dist: PySide6 (==6.5.0)
Requires-Dist: braveblock (==0.5.0)
Requires-Dist: plyer (==2.1.0)
Requires-Dist: pypiwin32 (==223) ; sys_platform == "win32"
Requires-Dist: sqlalchemy (==2.0.6)
Requires-Dist: winshell (==0.6) ; sys_platform == "win32"
Project-URL: Repository, https://codeberg.org/OneEyedDancer/Devoud
